cercalia/__init__.py
cercalia/config.py
cercalia/services/__init__.py
cercalia/services/cercalia_client.py
cercalia/services/geocoding_service.py
cercalia/services/geofencing_service.py
cercalia/services/geoment_service.py
cercalia/services/isochrone_service.py
cercalia/services/poi_service.py
cercalia/services/proximity_service.py
cercalia/services/reversegeocoding_service.py
cercalia/services/routing_service.py
cercalia/services/snaptoroad_service.py
cercalia/services/staticmaps_service.py
cercalia/services/suggest_service.py
cercalia/types/__init__.py
cercalia/types/api_response.py
cercalia/types/common.py
cercalia/types/geocoding.py
cercalia/types/geofencing.py
cercalia/types/geoment.py
cercalia/types/isochrone.py
cercalia/types/poi.py
cercalia/types/proximity.py
cercalia/types/reversegeocoding.py
cercalia/types/routing.py
cercalia/types/snaptoroad.py
cercalia/types/staticmaps.py
cercalia/types/suggest.py
cercalia/utils/__init__.py
cercalia/utils/logger.py
cercalia/utils/retry.py
cercalia_sdk-1.0.0rc1.dist-info/METADATA
cercalia_sdk-1.0.0rc1.dist-info/WHEEL
cercalia_sdk-1.0.0rc1.dist-info/top_level.txt
cercalia_sdk-1.0.0rc1.dist-info/RECORD
