Metadata-Version: 2.4
Name: cercalia-sdk
Version: 1.0.0rc1
Summary: Pure Python SDK for Cercalia Web Services
Author-email: Cercalia <info@cercalia.com>
License: MIT
Project-URL: Homepage, https://www.cercalia.com/
Project-URL: Documentation, https://docs.cercalia.com/docs/
Project-URL: Repository, https://github.com/cercalia/cercalia-sdk-python
Project-URL: Issues, https://github.com/cercalia/cercalia-sdk-python/issues
Keywords: cercalia,geocoding,routing,geospatial,maps,gis,reverse-geocoding,isochrone,poi
Classifier: Development Status :: 4 - Beta
Classifier: Intended Audience :: Developers
Classifier: License :: OSI Approved :: MIT License
Classifier: Programming Language :: Python :: 3
Classifier: Programming Language :: Python :: 3.9
Classifier: Programming Language :: Python :: 3.10
Classifier: Programming Language :: Python :: 3.11
Classifier: Programming Language :: Python :: 3.12
Classifier: Programming Language :: Python :: 3.13
Classifier: Topic :: Software Development :: Libraries :: Python Modules
Classifier: Topic :: Scientific/Engineering :: GIS
Classifier: Typing :: Typed
Requires-Python: >=3.9
Requires-Dist: requests>=2.31.0
Requires-Dist: pydantic>=2.5.0
Provides-Extra: dev
Requires-Dist: pytest>=7.4.0; extra == "dev"
Requires-Dist: pytest-cov>=4.1.0; extra == "dev"
Requires-Dist: mypy>=1.7.0; extra == "dev"
Requires-Dist: ruff>=0.1.0; extra == "dev"
Requires-Dist: types-requests>=2.31.0; extra == "dev"
Provides-Extra: docs
Requires-Dist: pdoc>=16.0.0; extra == "docs"
